mem_w.v
module mem_w(clk,mem_ena,wr_rd,addr,data_in,data_out);
  input  clk,mem_ena,wr_rd;
  input  [6:0] addr;
  input  [15:0] data_in;
  output [15:0] data_out;

  reg    [15:0] data_out;
  reg    [15:0] mem [(2**6)-1:0];

  //read data
  integer file, j, flag;
  real f;
  initial
  begin
    file = $fopen("weight.txt","r");
    flag = $fscanf(file, "%f", f);
    j = 0;
    while(j<=63 && flag!=0)
    begin
      mem[j] = f*512;
      $display("weight:%d", mem[j]);
      flag = $fscanf(file, "%f", f);
      j = j + 1;
    end
    $fclose(file);
  end

  always @(posedge clk)
    if(mem_ena)
      if(wr_rd)
      begin
        mem[addr] <= data_in;
      end
      else
        data_out  <= mem[addr];
endmodule

mem_data_label.v
module mem_data_label(clk,mem_ena,wr_rd,addr,data_in,data_out);
  input  clk,mem_ena,wr_rd;
  input  [10:0] addr;
  input  [15:0] data_in;
  output [15:0] data_out;

  reg    [15:0] data_out;
  reg    [15:0] mem [(2**10)-1:0];

  //read data
  integer file, j, flag;
  real f;
  initial
  begin
    file = $fopen("output.txt","r");
    flag = $fscanf(file, "%f", f);
    j = 0;
    while(j<=1023 && flag!=0)
    begin
      mem[j] = f*512;
      $display("input:%d,j=%d,flag=%d", mem[j],j,flag);
      flag = $fscanf(file, "%f", f);
      j = j + 1;
    end
    $fclose(file);
  end

  always @(posedge clk)
    if(mem_ena)
      if(wr_rd)
      begin
        mem[addr] <= data_in;
      end
      else
        data_out  <= mem[addr];
endmodule

mem_data_x2.v
module mem_data_x2(clk,mem_ena,wr_rd,addr,data_in,data_out);
  input  clk,mem_ena,wr_rd;
  input  [10:0] addr;
  input  [15:0] data_in;
  output [15:0] data_out;

  reg    [15:0] data_out;
  reg    [15:0] mem [(2**10)-1:0];

  //read data
  integer file, j, flag;
  real f;
  initial
  begin
    file = $fopen("inputx2.txt","r");
    flag = $fscanf(file, "%f", f);
    j = 0;
    while(j<=1023 && flag!=0)
    begin
      mem[j] = f*512;
      $display("input:%d,j=%d,flag=%d", mem[j],j,flag);
      flag = $fscanf(file, "%f", f);
      j = j + 1;
    end
    $fclose(file);
  end

  always @(posedge clk)
    if(mem_ena)
      if(wr_rd)
      begin
        mem[addr] <= data_in;
      end
      else
        data_out  <= mem[addr];
endmodule

mem_data_x1.v
module mem_data_x1(clk,mem_ena,wr_rd,addr,data_in,data_out);
  input  clk,mem_ena,wr_rd;
  input  [10:0] addr;
  input  [15:0] data_in;
  output [15:0] data_out;

  reg    [15:0] data_out;
  reg    [15:0] mem [(2**10)-1:0];

  //read data
  integer file, j, flag;
  real f;
  initial
  begin
    file = $fopen("inputx1.txt","r");
    flag = $fscanf(file, "%f", f);
    j = 0;
    while(j<=1023 && flag!=0)
    begin
      mem[j] = f*512;
      $display("input:%d,j=%d,flag=%d", mem[j],j,flag);
      flag = $fscanf(file, "%f", f);
      j = j + 1;
    end
    $fclose(file);
  end

  always @(posedge clk)
    if(mem_ena)
      if(wr_rd)
      begin
        mem[addr] <= data_in;
      end
      else
        data_out  <= mem[addr];
endmodule

PER_core.v
module PER_core(clk,rst,control,mem_x1_ena,mem_x1_addr,mem_x1_data,mem_x1_w,mem_x2_ena,mem_x2_addr,mem_x2_data,mem_x2_w,
               mem_label_ena,mem_label_addr,mem_label_data,mem_label_w,mem_w_ena,mem_w_addr,mem_w_data,mem_w_w,mem_w_data_out);
  input clk;
  input rst;

  input [3: 0] control;
  input [15:0] mem_x1_data,mem_x2_data,mem_label_data;
  input [10:0] mem_x1_addr,mem_x2_addr,mem_label_addr;
  output reg   mem_x1_ena ,mem_x2_ena ,mem_label_ena;
  output reg   mem_x1_w   ,mem_x2_w   ,mem_label_w;
  reg signed [15:0] mem_x1_r,mem_x2_r,mem_label_r;
  //reg   [7 :0] mem_x1_addr,mem_x2_addr,mem_label_addr;
  input [15:0] mem_w_data;
  output[15:0] mem_w_data_out;
  output[6 :0] mem_w_addr;
  output reg   mem_w_ena,mem_w_w;
  reg   [6 :0] mem_w_addr;
  reg   [15:0] w1_data_out,w2_data_out,b_data_out,mem_w_data_out;
  reg signed [15:0] w1,w2,b;

  reg end_of_w;
  reg end_of_up;
  reg end_of_rd;
  reg signed [31:0] mult;
  reg signed [31:0] sum;
  reg signed [15:0] differ;
  reg F;
  //reg [7:0] cont;

  //主状态机
  parameter start     = 5'b00001,
            readdata  = 5'b00010,
            calculate = 5'b00100,
            update    = 5'b01000,
            finish    = 5'b10000,
            //读取数据状态机
            rd_idle   = 5'b00001,
            rd_axis1  = 5'b00010,
            rd_axis2  = 5'b00100,
            rd_bias   = 5'b01000,
            rd_end    = 5'b10000,
            //计算向量积状态机
            cal_idle  = 8'b00000001,
            cal_axis1 = 8'b00000010,
            cal_axis2 = 8'b00000100,
            cal_sum   = 8'b00001000,
            cal_bias  = 8'b00010000,
            cal_F     = 8'b00100000,
            cal_differ= 8'b01000000,
            cal_end   = 8'b10000000,
            //更新向量积状态机
            upd_idle  = 6'b000001,
            upd_bias  = 6'b000010,
            upd_axis2 = 6'b000100,
            upd_axis1 = 6'b001000,
            upd_wr    = 6'b010000,
            upd_end   = 6'b100000;

  reg[5:0] state;
  reg[5:0] read_state;
  reg[8:0] calculate_state;
  reg[6:0] update_state;

  always @(posedge clk)
  begin
    if(rst)
    begin
      state          <= start;
      read_state     <= 6'bxxxxxx;
      calculate_state<= 9'bxxxxxxxxx;
      update_state   <= 7'bxxxxxxx;
      end_of_w       <= 0;
      end_of_up      <= 0;
      end_of_rd      <= 0;
      mem_w_addr     <= 0;
      mem_x1_ena     <= 1;
      mem_x2_ena     <= 1;
      mem_label_ena  <= 1;
      mem_w_ena      <= 1;
      mem_x1_w       <= 0;
      mem_x2_w       <= 0;
      mem_label_w    <= 0;
      mem_w_w        <= 0;
      mem_x1_r       <= mem_x1_data;
      mem_x2_r       <= mem_x2_data;
      mem_label_r    <= mem_label_data/512;
    /*mem_x1_addr    <= 0;
      mem_x2_addr    <= 0;
      mem_label_addr <= 0;
      cont           <= 0;*/
    end
    else
    begin
      case(state)
        start: 
               if(control[0]==1)
               begin
                 state <= readdata;
               end
               else
               begin
                 state <= start;
               end
        readdata:
               if(control[1]==1 && end_of_rd)
               begin
                 state <= calculate;
               end
               else
               begin
                 read_state <= rd_idle;
                 reading;
                 state      <= readdata;
               end
        calculate: 
               if(control[2]==1 && end_of_w)
               begin
                 state <= update;
               end
               else
               begin
                 calculate_state <= cal_idle;
                 calculating;
                 state           <= calculate;
               end
        update:
               if(control[3]==1 && end_of_up)
               begin
                 state <= finish;
               end
               else
               begin
                 update_state <= upd_idle;
                 updating;
                 state        <= update;
               end
        finish:
               begin
                 state <= start;
               end
        default:
               state <= start;
      endcase
    end
  end

task reading;
  begin
    case(read_state)
      rd_idle:
        begin
          end_of_rd  <= 0;
          read_state <= rd_axis1;
          mem_w_addr <= mem_w_addr+1;
        end
      rd_axis1:
        begin
          w1         <= mem_w_data;
          mem_w_addr <= mem_w_addr+1;
          read_state <= rd_axis2;
        end
      rd_axis2:
        begin
          w2         <= mem_w_data;
          //mem_w_addr <= mem_w_addr+1;
          read_state <= rd_bias;
        end
      rd_bias:
        begin
          b          <= mem_w_data;
          read_state <= rd_end;
        end
      rd_end:
        begin
          end_of_rd  <= 1;
          read_state <= rd_idle;
        end
      default:
        begin
          read_state <= rd_idle;
        end
    endcase
  end
endtask
                       
task calculating;
  begin
    case(calculate_state)
      cal_idle:
        begin
          sum             <= 32'b0;
          differ          <= 32'b0;
          mult            <= 32'b0;
          end_of_w        <= 0;
          calculate_state <= cal_axis1;
        end
      cal_axis1:
        begin
          mult            <= w1*mem_x1_r;
        //sum             <= sum+mult;
          calculate_state <= cal_axis2;
        end
      cal_axis2:
        begin
          mult            <= w2*mem_x2_r;
          sum             <= sum+mult;
          calculate_state <= cal_sum;
        end
      cal_sum:
        begin
          sum             <= sum+mult;
          calculate_state <= cal_bias;
        end
      cal_bias:
        begin
          sum             <= sum+b;
          calculate_state <= cal_F;
        end
      cal_F:
        begin
          F               <= (sum>=0)? 1 : 0;
          calculate_state <= cal_differ;
        end
      cal_differ:
        begin
          differ          <= mem_label_r-F;
          calculate_state <= cal_end;
        end
      cal_end:
        begin
          end_of_w        <= 1;
          calculate_state <= cal_idle;
        end
      default:
        begin
          calculate_state <= cal_idle;
        end
    endcase
  end
endtask

task updating;
  begin
    case(update_state)
      upd_idle:
        begin
          update_state   <= upd_bias;
          end_of_up      <= 0;
          mem_w_w        <= 1;
        end
      upd_bias:
        begin
          b_data_out     <= b+differ*512;
        //mem_w_w        <= 1;
        //mem_w_data_out <= b_data_out;
        //mem_w_addr     <= mem_w_addr-1;
          update_state   <= upd_axis2;
        end
      upd_axis2:
        begin
          w2_data_out    <= w2+differ*mem_x2_r;
          mem_w_data_out <= b_data_out;
        //mem_w_addr     <= mem_w_addr-1;
          update_state   <= upd_axis1;
        end
      upd_axis1:
        begin
          w1_data_out    <= w1+differ*mem_x1_r;
          mem_w_addr     <= mem_w_addr-1;
          mem_w_data_out <= w2_data_out;
          update_state   <= upd_wr;
        end
      upd_wr:
        begin
          mem_w_data_out <= w1_data_out;
          mem_w_addr     <= mem_w_addr-1;
          update_state   <= upd_end;
        end
      upd_end:
        begin
          end_of_up      <= 1;
          mem_w_w        <= 0;
          update_state   <= upd_idle;
        end
      default:
        begin
          update_state <= upd_idle;
        end
    endcase
  end
endtask

endmodule

PER_top.v
module PER_top();
  reg  clk;
  reg  rst;
  reg  [3:0] control;
  wire mem_x1_w,mem_x2_w,mem_label_w,mem_w_w;
  wire mem_x1_ena,mem_x2_ena,mem_label_ena,mem_w_ena;
  wire [15:0] mem_x1_data,mem_x2_data,mem_label_data,mem_w_data,mem_w_data_out;
  reg  [10:0] mem_x1_addr,mem_x2_addr,mem_label_addr;
  wire [6 :0] mem_w_addr;
  reg  [15:0] mem_x1_data_in,mem_x2_data_in,mem_label_data_in;

  PER_core core(clk,rst,control,mem_x1_ena,mem_x1_addr,mem_x1_data,mem_x1_w,mem_x2_ena,mem_x2_addr,mem_x2_data,mem_x2_w,
               mem_label_ena,mem_label_addr,mem_label_data,mem_label_w,mem_w_ena,mem_w_addr,mem_w_data,mem_w_w,mem_w_data_out);

  mem_data_x1 x1(clk,mem_x1_ena,mem_x1_w,mem_x1_addr,mem_x1_data_in,mem_x1_data);

  mem_data_x2 x2(clk,mem_x2_ena,mem_x2_w,mem_x2_addr,mem_x2_data_in,mem_x2_data);

  mem_data_label label(clk,mem_label_ena,mem_label_w,mem_label_addr,mem_label_data_in,mem_label_data);

  mem_w weight(clk,mem_w_ena,mem_w_w,mem_w_addr,mem_w_data_out,mem_w_data);

  always
    begin
      clk=1; #5; clk=0; #5;
    end

  initial 
    begin
      rst            <= 0;
      control        <= 0;
      #10;
      rst            <= 1;
      mem_x1_addr    <= 0;
      mem_x2_addr    <= 0;
      mem_label_addr <= 0;
      #50;
      rst            <= 0;
      control        <= 4'b1111;
      #300;
      repeat(500) begin
      rst            <= 0;
      control        <= 0;
      #10;
      rst            <= 1;
      mem_x1_addr    <= mem_x1_addr+1;
      mem_x2_addr    <= mem_x2_addr+1;
      mem_label_addr <= mem_label_addr+1;
      #50;
      rst            <= 0;
      control        <= 4'b1111;
      #300;
      end
      $finish;
    end

  initial 
    begin
      $dumpfile("PER.vcd");
      $dumpvars(0,PER_top);
    end

endmodule

PER.vcd
$date
	Tue Jul  9 15:47:31 2019
$end
$version
	Icarus Verilog
$end
$timescale
	1s
$end
$scope module PER_top $end
$var wire 1 ! mem_x2_w $end
$var wire 1 " mem_x2_ena $end
$var wire 16 # mem_x2_data [15:0] $end
$var wire 1 $ mem_x1_w $end
$var wire 1 % mem_x1_ena $end
$var wire 16 & mem_x1_data [15:0] $end
$var wire 1 ' mem_w_w $end
$var wire 1 ( mem_w_ena $end
$var wire 16 ) mem_w_data_out [15:0] $end
$var wire 16 * mem_w_data [15:0] $end
$var wire 7 + mem_w_addr [6:0] $end
$var wire 1 , mem_label_w $end
$var wire 1 - mem_label_ena $end
$var wire 16 . mem_label_data [15:0] $end
$var reg 1 / clk $end
$var reg 4 0 control [3:0] $end
$var reg 11 1 mem_label_addr [10:0] $end
$var reg 16 2 mem_label_data_in [15:0] $end
$var reg 11 3 mem_x1_addr [10:0] $end
$var reg 16 4 mem_x1_data_in [15:0] $end
$var reg 11 5 mem_x2_addr [10:0] $end
$var reg 16 6 mem_x2_data_in [15:0] $end
$var reg 1 7 rst $end
$scope module core $end
$var wire 1 / clk $end
$var wire 4 8 control [3:0] $end
$var wire 11 9 mem_label_addr [10:0] $end
$var wire 11 : mem_x1_addr [10:0] $end
$var wire 11 ; mem_x2_addr [10:0] $end
$var wire 1 7 rst $end
$var wire 16 < mem_x2_data [15:0] $end
$var wire 16 = mem_x1_data [15:0] $end
$var wire 16 > mem_w_data [15:0] $end
$var wire 16 ? mem_label_data [15:0] $end
$var reg 1 @ F $end
$var reg 16 A b [15:0] $end
$var reg 16 B b_data_out [15:0] $end
$var reg 9 C calculate_state [8:0] $end
$var reg 16 D differ [15:0] $end
$var reg 1 E end_of_rd $end
$var reg 1 F end_of_up $end
$var reg 1 G end_of_w $end
$var reg 1 - mem_label_ena $end
$var reg 16 H mem_label_r [15:0] $end
$var reg 1 , mem_label_w $end
$var reg 7 I mem_w_addr [6:0] $end
$var reg 16 J mem_w_data_out [15:0] $end
$var reg 1 ( mem_w_ena $end
$var reg 1 ' mem_w_w $end
$var reg 1 % mem_x1_ena $end
$var reg 16 K mem_x1_r [15:0] $end
$var reg 1 $ mem_x1_w $end
$var reg 1 " mem_x2_ena $end
$var reg 16 L mem_x2_r [15:0] $end
$var reg 1 ! mem_x2_w $end
$var reg 32 M mult [31:0] $end
$var reg 6 N read_state [5:0] $end
$var reg 6 O state [5:0] $end
$var reg 32 P sum [31:0] $end
$var reg 7 Q update_state [6:0] $end
$var reg 16 R w1 [15:0] $end
$var reg 16 S w1_data_out [15:0] $end
$var reg 16 T w2 [15:0] $end
$var reg 16 U w2_data_out [15:0] $end
$scope task calculating $end
$upscope $end
$scope task reading $end
$upscope $end
$scope task updating $end
$upscope $end
$upscope $end
$scope module label $end
$var wire 11 V addr [10:0] $end
$var wire 1 / clk $end
$var wire 16 W data_in [15:0] $end
$var wire 1 - mem_ena $end
$var wire 1 , wr_rd $end
$var reg 16 X data_out [15:0] $end
$var real 1 Y f $end
$var integer 32 Z file [31:0] $end
$var integer 32 [ flag [31:0] $end
$var integer 32 \ j [31:0] $end
$upscope $end
$scope module weight $end
$var wire 7 ] addr [6:0] $end
$var wire 1 / clk $end
$var wire 16 ^ data_in [15:0] $end
$var wire 1 ( mem_ena $end
$var wire 1 ' wr_rd $end
$var reg 16 _ data_out [15:0] $end
$var real 1 ` f $end
$var integer 32 a file [31:0] $end
$var integer 32 b flag [31:0] $end
$var integer 32 c j [31:0] $end
$upscope $end
$scope module x1 $end
$var wire 11 d addr [10:0] $end
$var wire 1 / clk $end
$var wire 16 e data_in [15:0] $end
$var wire 1 % mem_ena $end
$var wire 1 $ wr_rd $end
$var reg 16 f data_out [15:0] $end
$var real 1 g f $end
$var integer 32 h file [31:0] $end
$var integer 32 i flag [31:0] $end
$var integer 32 j j [31:0] $end
$upscope $end
$scope module x2 $end
$var wire 11 k addr [10:0] $end
$var wire 1 / clk $end
$var wire 16 l data_in [15:0] $end
$var wire 1 " mem_ena $end
$var wire 1 ! wr_rd $end
$var reg 16 m data_out [15:0] $end
$var real 1 n f $end
$var integer 32 o file [31:0] $end
$var integer 32 p flag [31:0] $end
$var integer 32 q j [31:0] $end
$upscope $end
$upscope $end
$enddefinitions $end
#0
$dumpvars
b111110100 q
b0 p
b10000000000000000000000000000011 o
r-0.17 n
bx m
bx l
bx k
b111110100 j
b0 i
b10000000000000000000000000000011 h
r0.24 g
bx f
bx e
bx d
b11 c
b0 b
b10000000000000000000000000000011 a
r0.5 `
bx _
bx ^
bx ]
b111110100 \
b0 [
b10000000000000000000000000000011 Z
r1 Y
bx X
bx W
bx V
bx U
bx T
bx S
bx R
bx Q
bx P
b1 O
bx N
bx M
bx L
bx K
bx J
bx I
bx H
xG
xF
xE
bx D
bx C
bx B
bx A
x@
bx ?
bx >
bx =
bx <
bx ;
bx :
bx 9
b0 8
07
bx 6
bx 5
bx 4
bx 3
bx 2
bx 1
b0 0
1/
bx .
x-
x,
bx +
bx *
bx )
x(
x'
bx &
x%
x$
bx #
x"
x!
$end
#5
0/
#10
b0 1
b0 9
b0 V
b0 5
b0 ;
b0 k
b0 3
b0 :
b0 d
17
1/
#15
0/
#20
0'
0,
0!
0$
1(
1-
1"
1%
b0 +
b0 I
b0 ]
0E
0F
0G
1/
#25
0/
#30
b10011010 *
b10011010 >
b10011010 _
b1000000000 .
b1000000000 ?
b1000000000 X
b1111110100111000 #
b1111110100111000 <
b1111110100111000 m
b11101010111 &
b11101010111 =
b11101010111 f
1/
#35
0/
#40
b1 H
b1111110100111000 L
b11101010111 K
1/
#45
0/
#50
1/
#55
0/
#60
b1111 0
b1111 8
07
1/
#65
0/
#70
b10 O
1/
#75
0/
#80
b1 N
1/
#85
0/
#90
b1 +
b1 I
b1 ]
b10 N
1/
#95
0/
#100
b10 +
b10 I
b10 ]
b10011010 R
b11001101 *
b11001101 >
b11001101 _
b100 N
1/
#105
0/
#110
b11001101 T
b100000000 *
b100000000 >
b100000000 _
b1000 N
1/
#115
0/
#120
b100000000 A
b10000 N
1/
#125
0/
#130
1E
b1 N
1/
#135
0/
#140
b100 O
1/
#145
0/
#150
b1 C
1/
#155
0/
#160
b10 C
b0 M
b0 D
b0 P
1/
#165
0/
#170
b1000110101001010110 M
b100 C
1/
#175
0/
#180
b1000110101001010110 P
b11111111111111011100010111011000 M
b1000 C
1/
#185
0/
#190
b100011000000101110 P
b10000 C
1/
#195
0/
#200
b100011000100101110 P
b100000 C
1/
#205
0/
#210
1@
b1000000 C
1/
#215
0/
#220
b10000000 C
1/
#225
0/
#230
1G
b1 C
1/
#235
0/
#240
b1000 O
1/
#245
0/
#250
b1 Q
1/
#255
0/
#260
1'
b10 Q
1/
#265
0/
#270
b100000000 B
b100 Q
1/
#275
0/
#280
b100000000 )
b100000000 J
b100000000 ^
b11001101 U
b1000 Q
1/
#285
0/
#290
b11001101 )
b11001101 J
b11001101 ^
b1 +
b1 I
b1 ]
b10011010 S
b10000 Q
1/
#295
0/
#300
b0 +
b0 I
b0 ]
b10011010 )
b10011010 J
b10011010 ^
b100000 Q
1/
#305
0/
#310
0'
1F
b1 Q
1/
#315
0/
#320
b10011010 *
b10011010 >
b10011010 _
b10000 O
1/
#325
0/
#330
b1 O
1/
#335
0/
#340
b10 O
1/
#345
0/
#350
b100 O
1/
#355
0/
#360
b1000 O
b0 0
b0 8
1/
#365
0/
#370
1'
0F
b10 Q
b1 1
b1 9
b1 V
b1 5
b1 ;
b1 k
b1 3
b1 :
b1 d
17
1/
#375
0/
#380
b1001001101 &
b1001001101 =
b1001001101 f
b10110101110 #
b10110101110 <
b10110101110 m
b0 .
b0 ?
b0 X
0'
0E
0G
bx Q
bx C
bx N
b1 O
1/
#385
0/
#390
b0 H
b10110101110 L
b1001001101 K
1/
#395
0/
#400
1/
#405
0/
#410
1/
#415
0/
#420
b1111 0
b1111 8
07
1/
#425
0/
#430
b10 O
1/
#435
0/
#440
b1 N
1/
#445
0/
#450
b1 +
b1 I
b1 ]
b10 N
1/
#455
0/
#460
b10 +
b10 I
b10 ]
b11001101 *
b11001101 >
b11001101 _
b100 N
1/
#465
0/
#470
b100000000 *
b100000000 >
b100000000 _
b1000 N
1/
#475
0/
#480
b10000 N
1/
#485
0/
#490
1E
b1 N
1/
#495
0/
#500
b100 O
1/
#505
0/
#510
b1 C
1/
#515
0/
#520
b10 C
b0 M
b0 P
1/
#525
0/
#530
b10110001001010010 M
b100 C
1/
#535
0/
#540
b10110001001010010 P
b1001000110001010110 M
b1000 C
1/
#545
0/
#550
b1011110111010101000 P
b10000 C
1/
#555
0/
#560
b1011110111110101000 P
b100000 C
1/
#565
0/
#570
b1000000 C
1/
#575
0/
#580
b1111111111111111 D
b10000000 C
1/
#585
0/
#590
1G
b1 C
1/
#595
0/
#600
b1000 O
1/
#605
0/
#610
b1 Q
1/
#615
0/
#620
1'
b10 Q
1/
#625
0/
#630
b1111111100000000 B
b100 Q
1/
#635
0/
#640
b1111111100000000 )
b1111111100000000 J
b1111111100000000 ^
b1111101100011111 U
b1000 Q
1/
#645
0/
#650
b1111101100011111 )
b1111101100011111 J
b1111101100011111 ^
b1 +
b1 I
b1 ]
b1111111001001101 S
b10000 Q
1/
#655
0/
#660
b0 +
b0 I
b0 ]
b1111111001001101 )
b1111111001001101 J
b1111111001001101 ^
b100000 Q
1/
#665
0/
#670
0'
1F
b1 Q
1/
#675
0/
#680
b1111111001001101 *
b1111111001001101 >
b1111111001001101 _
b10000 O
1/
#685
0/
#690
b1 O
1/
#695
0/
#700
b10 O
1/
#705
0/
#710
b100 O
1/
#715
0/
#720
b1000 O
b0 0
b0 8
1/
#725
0/
#730
1'
0F
b10 Q
b10 1
b10 9
b10 V
b10 5
b10 ;
b10 k
b10 3
b10 :
b10 d
17
1/
#735
0/
#740
b1111101001111011 &
b1111101001111011 =
b1111101001111011 f
b11011000011 #
b11011000011 <
b11011000011 m
0'
0E
0G
bx Q
bx C
bx N
b1 O
1/
#745
0/
#750
b11011000011 L
b1111101001111011 K
1/
#755
0/
#760
1/
#765
0/
#770
1/
#775
0/
#780
b1111 0
b1111 8
07
1/
#785
0/
#790
b10 O
1/
#795
0/
#800
b1 N
1/
#805
0/
#810
b1 +
b1 I
b1 ]
b10 N
1/
#815
0/
#820
b10 +
b10 I
b10 ]
b1111111001001101 R
b1111101100011111 *
b1111101100011111 >
b1111101100011111 _
b100 N
1/
#825
0/
#830
b1111101100011111 T
b1111111100000000 *
b1111111100000000 >
b1111111100000000 _
b1000 N
1/
#835
0/
#840
b1111111100000000 A
b10000 N
1/
#845
0/
#850
1E
b1 N
1/
#855
0/
#860
b100 O
1/
#865
0/
#870
b1 C
1/
#875
0/
#880
b10 C
b0 M
b0 D
b0 P
1/
#885
0/
#890
b10010110000011111111 M
b100 C
1/
#895
0/
#900
b10010110000011111111 P
b11111111110111110000001010011101 M
b1000 C
1/
#905
0/
#910
b11111111111010000110001110011100 P
b10000 C
1/
#915
0/
#920
b11111111111010000110001010011100 P
b100000 C
1/
#925
0/
#930
0@
b1000000 C
1/
#935
0/
#940
b10000000 C
1/
#945
0/
#950
1G
b1 C
1/
#955
0/
#960
b1000 O
1/
#965
0/
#970
b1 Q
1/
#975
0/
#980
1'
b10 Q
1/
#985
0/
#990
b100 Q
1/
#995
0/
#1000
b1111111100000000 )
b1111111100000000 J
b1111111100000000 ^
b1000 Q
1/
#1005
0/
#1010
b1111101100011111 )
b1111101100011111 J
b1111101100011111 ^
b1 +
b1 I
b1 ]
b10000 Q
1/
#1015
0/
#1020
b0 +
b0 I
b0 ]
b1111111001001101 )
b1111111001001101 J
b1111111001001101 ^
b100000 Q
1/
#1025
0/
#1030
0'
1F
b1 Q
1/
#1035
0/
#1040
b1111111001001101 *
b1111111001001101 >
b1111111001001101 _
b10000 O
1/
#1045
0/
#1050
b1 O
1/
#1055
0/
#1060
b10 O
1/
#1065
0/
#1070
b100 O
1/
#1075
0/
#1080
b1000 O
b0 0
b0 8
1/
#1085
0/
#1090
1'
0F
b10 Q
b11 1
b11 9
b11 V
b11 5
b11 ;
b11 k
b11 3
b11 :
b11 d
17
1/
#1095
0/
#1100
b1111011111100001 &
b1111011111100001 =
b1111011111100001 f
b11001010111 #
b11001010111 <
b11001010111 m
0'
0E
0G
bx Q
bx C
bx N
b1 O
1/
#1105
0/
#1110
b11001010111 L
b1111011111100001 K
1/
#1115
0/
#1120
1/
#1125
0/
#1130
1/
#1135
0/
#1140
b1111 0
b1111 8
07
1/
#1145
0/
#1150
b10 O
1/
#1155
0/
#1160
b1 N
1/
#1165
0/
#1170
b1 +
b1 I
b1 ]
b10 N
1/
#1175
0/
#1180
b10 +
b10 I
b10 ]
b1111101100011111 *
b1111101100011111 >
b1111101100011111 _
b100 N
1/
#1185
0/
#1190
b1111111100000000 *
b1111111100000000 >
b1111111100000000 _
b1000 N
1/
#1195
0/
#1200
b10000 N
1/
#1205
0/
#1210
1E
b1 N
1/
#1215
0/
#1220
b100 O
1/
#1225
0/
#1230
b1 C
1/
#1235
0/
#1240
b10 C
b0 M
b0 P
1/
#1245
0/
#1250
b11011100110010101101 M
b100 C
1/
#1255
0/
#1260
b11011100110010101101 P
b11111111111000010001000110001001 M
b1000 C
1/
#1265
0/
#1270
b11111111111011101101111000110110 P
b10000 C
1/
#1275
0/
#1280
b11111111111011101101110100110110 P
b100000 C
1/
#1285
0/
#1290
b1000000 C
1/
#1295
0/
#1300
b10000000 C
1/
#1305
0/
#1310
1G
b1 C
1/
#1315
0/
#1320
b1000 O
1/
#1325
0/
#1330
b1 Q
1/
#1335
0/
#1340
1'
b10 Q
1/
#1345
0/
#1350
b100 Q
1/
#1355
0/
#1360
b1111111100000000 )
b1111111100000000 J
b1111111100000000 ^
b1000 Q
1/
#1365
0/
#1370
b1111101100011111 )
b1111101100011111 J
b1111101100011111 ^
b1 +
b1 I
b1 ]
b10000 Q
1/
#1375
0/
#1380
b0 +
b0 I
b0 ]
b1111111001001101 )
b1111111001001101 J
b1111111001001101 ^
b100000 Q
1/
#1385
0/
#1390
0'
1F
b1 Q
1/
#1395
0/
#1400
b1111111001001101 *
b1111111001001101 >
b1111111001001101 _
b10000 O
1/
#1405
0/
#1410
b1 O
1/
#1415
0/
#1420
b10 O
1/
#1425
0/
#1430
b100 O
1/
#1435
0/
#1440
b1000 O
b0 0
b0 8
1/
#1445
0/
#1450
1'
0F
b10 Q
b100 1
b100 9
b100 V
b100 5
b100 ;
b100 k
b100 3
b100 :
b100 d
17
1/
#1455
0/
#1460
b11111000011 &
b11111000011 =
b11111000011 f
b10000111101 #
b10000111101 <
b10000111101 m
b1000000000 .
b1000000000 ?
b1000000000 X
0'
0E
0G
bx Q
bx C
bx N
b1 O
1/
#1465
0/
#1470
b1 H
b10000111101 L
b11111000011 K
1/
#1475
0/
#1480
1/
#1485
0/
#1490
1/
#1495
0/
#1500
b1111 0
b1111 8
07
1/
#1505
0/
#1510
b10 O
1/
#1515
0/
#1520
b1 N
1/
#1525
0/
#1530
b1 +
b1 I
b1 ]
b10 N
1/
#1535
0/
#1540
b10 +
b10 I
b10 ]
b1111101100011111 *
b1111101100011111 >
b1111101100011111 _
b100 N
1/
#1545
0/
#1550
b1111111100000000 *
b1111111100000000 >
b1111111100000000 _
b1000 N
1/
#1555
0/
#1560
b10000 N
1/
#1565
0/
#1570
1E
b1 N
1/
#1575
0/
#1580
b100 O
1/
#1585
0/
#1590
b1 C
1/
#1595
0/
#1600
b10 C
b0 M
b0 P
1/
#1605
0/
#1610
b11111111111100101100111110100111 M
b100 C
1/
#1615
0/
#1620
b11111111111100101100111110100111 P
b11111111111010110101001001100011 M
b1000 C
1/
#1625
0/
#1630
b11111111110111100010001000001010 P
b10000 C
1/
#1635
0/
#1640
b11111111110111100010000100001010 P
b100000 C
1/
#1645
0/
#1650
b1000000 C
1/
#1655
0/
#1660
b1 D
b10000000 C
1/
#1665
0/
#1670
1G
b1 C
1/
#1675
0/
#1680
b1000 O
1/
#1685
0/
#1690
b1 Q
1/
#1695
0/
#1700
1'
b10 Q
1/
#1705
0/
#1710
b100000000 B
b100 Q
1/
#1715
0/
#1720
b100000000 )
b100000000 J
b100000000 ^
b1111111101011100 U
b1000 Q
1/
#1725
0/
#1730
b1111111101011100 )
b1111111101011100 J
b1111111101011100 ^
b1 +
b1 I
b1 ]
b11000010000 S
b10000 Q
1/
#1735
0/
#1740
b0 +
b0 I
b0 ]
b11000010000 )
b11000010000 J
b11000010000 ^
b100000 Q
1/
#1745
0/
#1750
0'
1F
b1 Q
1/
#1755
0/
#1760
b11000010000 *
b11000010000 >
b11000010000 _
b10000 O
1/
#1765
0/
#1770
b1 O
1/
#1775
0/
#1780
b10 O
1/
#1785
0/
#1790
b100 O
1/
#1795
0/
#1800
b1000 O
b0 0
b0 8
1/
#1805
0/
#1810
1'
0F
b10 Q
b101 1
b101 9
b101 V
b101 5
b101 ;
b101 k
b101 3
b101 :
b101 d
17
1/
#1815
0/
#1820
b11011100001 &
b11011100001 =
b11011100001 f
b100100101001 #
b100100101001 <
b100100101001 m
b0 .
b0 ?
b0 X
0'
0E
0G
bx Q
bx C
bx N
b1 O
1/
#1825
0/
#1830
b0 H
b100100101001 L
b11011100001 K
1/
#1835
0/
#1840
1/
#1845
0/
#1850
1/
#1855
0/
#1860
b1111 0
b1111 8
07
1/
#1865
0/
#1870
b10 O
1/
#1875
0/
#1880
b1 N
1/
#1885
0/
#1890
b1 +
b1 I
b1 ]
b10 N
1/
#1895
0/
#1900
b10 +
b10 I
b10 ]
b11000010000 R
b1111111101011100 *
b1111111101011100 >
b1111111101011100 _
b100 N
1/
#1905
0/
#1910
b1111111101011100 T
b100000000 *
b100000000 >
b100000000 _
b1000 N
1/
#1915
0/
#1920
b100000000 A
b10000 N
1/
#1925
0/
#1930
1E
b1 N
1/
#1935
0/
#1940
b100 O
1/
#1945
0/
#1950
b1 C
1/
#1955
0/
#1960
b10 C
b0 M
b0 D
b0 P
1/
#1965
0/
#1970
b1010011011010000010000 M
b100 C
1/
#1975
0/
#1980
b1010011011010000010000 P
b11111111111110100010000110111100 M
b1000 C
1/
#1985
0/
#1990
b1000111101010111001100 P
b10000 C
1/
#1995
0/
#2000
b1000111101011011001100 P
b100000 C
1/
#2005
0/
#2010
1@
b1000000 C
1/
#2015
0/
